WeiXueyuanGolangJiaocheng/README.md
WeiXueyuanGolangJiaocheng/__init__.py
WeiXueyuanGolangJiaocheng/__main__.py
WeiXueyuanGolangJiaocheng/file.epub
WeiXueyuanGolangJiaocheng/index.html
WeiXueyuanGolangJiaocheng/css/__init__.py
WeiXueyuanGolangJiaocheng/css/annotations.css
WeiXueyuanGolangJiaocheng/css/main.css
WeiXueyuanGolangJiaocheng/css/normalize.css
WeiXueyuanGolangJiaocheng/css/popup.css
WeiXueyuanGolangJiaocheng/font/__init__.py
WeiXueyuanGolangJiaocheng/font/fontello.eot
WeiXueyuanGolangJiaocheng/font/fontello.svg
WeiXueyuanGolangJiaocheng/font/fontello.ttf
WeiXueyuanGolangJiaocheng/font/fontello.woff
WeiXueyuanGolangJiaocheng/img/__init__.py
WeiXueyuanGolangJiaocheng/img/annotator-glyph-sprite.png
WeiXueyuanGolangJiaocheng/img/annotator-icon-sprite.png
WeiXueyuanGolangJiaocheng/img/apple-touch-icon.png
WeiXueyuanGolangJiaocheng/img/cancelfullscreen.png
WeiXueyuanGolangJiaocheng/img/close.png
WeiXueyuanGolangJiaocheng/img/fullscreen.png
WeiXueyuanGolangJiaocheng/img/loader.gif
WeiXueyuanGolangJiaocheng/img/menu-icon.png
WeiXueyuanGolangJiaocheng/img/save.png
WeiXueyuanGolangJiaocheng/img/saved.png
WeiXueyuanGolangJiaocheng/img/settings-s.png
WeiXueyuanGolangJiaocheng/img/settings.png
WeiXueyuanGolangJiaocheng/img/star.png
WeiXueyuanGolangJiaocheng/js/__init__.py
WeiXueyuanGolangJiaocheng/js/epub.js
WeiXueyuanGolangJiaocheng/js/epub.min.js
WeiXueyuanGolangJiaocheng/js/epub.min.map
WeiXueyuanGolangJiaocheng/js/hooks.min.js
WeiXueyuanGolangJiaocheng/js/hooks.min.map
WeiXueyuanGolangJiaocheng/js/reader.js
WeiXueyuanGolangJiaocheng/js/reader.js.map
WeiXueyuanGolangJiaocheng/js/reader.min.js
WeiXueyuanGolangJiaocheng/js/reader.min.map
WeiXueyuanGolangJiaocheng/js/hooks/__init__.py
WeiXueyuanGolangJiaocheng/js/hooks/extensions/__init__.py
WeiXueyuanGolangJiaocheng/js/hooks/extensions/highlight.js
WeiXueyuanGolangJiaocheng/js/libs/__init__.py
WeiXueyuanGolangJiaocheng/js/libs/jquery.min.js
WeiXueyuanGolangJiaocheng/js/libs/localforage.min.js
wei_xueyuan_golang_jiaocheng-2024.3.6.0.dist-info/METADATA
wei_xueyuan_golang_jiaocheng-2024.3.6.0.dist-info/WHEEL
wei_xueyuan_golang_jiaocheng-2024.3.6.0.dist-info/entry_points.txt
wei_xueyuan_golang_jiaocheng-2024.3.6.0.dist-info/top_level.txt
wei_xueyuan_golang_jiaocheng-2024.3.6.0.dist-info/RECORD
